protontricks/__init__.py
protontricks/_version.py
protontricks/config.py
protontricks/flatpak.py
protontricks/gui.py
protontricks/steam.py
protontricks/util.py
protontricks/winetricks.py
protontricks/_vdf/LICENSE
protontricks/_vdf/README.rst
protontricks/_vdf/__init__.py
protontricks/_vdf/vdict.py
protontricks/cli/__init__.py
protontricks/cli/desktop_install.py
protontricks/cli/launch.py
protontricks/cli/main.py
protontricks/cli/util.py
protontricks/data/__init__.py
protontricks/data/data/__init__.py
protontricks/data/data/icon_placeholder.png
protontricks/data/scripts/__init__.py
protontricks/data/scripts/bwrap_launcher.sh
protontricks/data/scripts/wine_launch.sh
protontricks/data/scripts/wineserver_keepalive.bat
protontricks/data/scripts/wineserver_keepalive.sh
protontricks/data/share/applications/__init__.py
protontricks/data/share/applications/protontricks-launch.desktop
protontricks/data/share/applications/protontricks.desktop
protontricks-1.13.1.data/data/share/applications/protontricks-launch.desktop
protontricks-1.13.1.data/data/share/applications/protontricks.desktop
protontricks-1.13.1.dist-info/licenses/LICENSE
protontricks-1.13.1.dist-info/METADATA
protontricks-1.13.1.dist-info/WHEEL
protontricks-1.13.1.dist-info/entry_points.txt
protontricks-1.13.1.dist-info/top_level.txt
protontricks-1.13.1.dist-info/RECORD
