Metadata-Version: 2.4
Name: protontricks
Version: 1.13.1
Summary: A simple wrapper for running Winetricks commands for Proton-enabled games.
Home-page: https://github.com/Matoking/protontricks
Author: Janne Pulkkinen
Author-email: janne.pulkkinen@protonmail.com
License: GPL3
Platform: linux
Classifier: License :: OSI Approved :: GNU General Public License v3 (GPLv3)
Classifier: Topic :: Utilities
Classifier: Programming Language :: Python
Classifier: Programming Language :: Python :: 3
Classifier: Programming Language :: Python :: 3.7
Classifier: Programming Language :: Python :: 3.8
Classifier: Programming Language :: Python :: 3.9
Classifier: Programming Language :: Python :: 3.10
Classifier: Programming Language :: Python :: 3.11
Classifier: Programming Language :: Python :: 3.12
Classifier: Programming Language :: Python :: 3.13
Classifier: Programming Language :: Python :: 3.14
Requires-Python: >=3.7
License-File: LICENSE
Requires-Dist: vdf>=3.2
Requires-Dist: Pillow
Dynamic: license-file
